LICENSE
fsai_coco_filter/fsai_coco_filter.py
fsai_coco_filter/tasks/filter_annotations.py
fsai_coco_filter/tasks/load_coco_json.py
fsai_coco_filter/tasks/reset_category_ids.py
fsai_coco_filter/tasks/save_coco_json.py
fsai_coco_filter/tasks/update_info.py
fsai_coco_filter-0.1.3.dist-info/entry_points.txt
fsai_coco_filter-0.1.3.dist-info/LICENSE
fsai_coco_filter-0.1.3.dist-info/WHEEL
fsai_coco_filter-0.1.3.dist-info/METADATA
fsai_coco_filter-0.1.3.dist-info/RECORD
